[
  {
    "id": "p1",
    "name": "Premium Leather Laptop Bag",
    "price": 149.99,
    "originalPrice": 189.99,
    "category": "bags",
    "subcategory": "laptop-bags",
    "image": "/images/p1.jpg",
    "images": ["/images/p1.jpg", "/images/p1-alt1.jpg", "/images/p1-alt2.jpg"],
    "rating": 4.7,
    "reviewCount": 127,
    "short": "Premium full-grain leather laptop bag with compartments for 15-inch laptops.",
    "description": "Crafted from the finest full-grain leather, this laptop bag combines functionality with timeless style. Features padded compartments for laptops up to 15 inches, multiple pockets for organization, and adjustable shoulder strap for comfort.",
    "features": [
      "Full-grain leather",
      "15-inch laptop compartment",
      "Multiple pockets",
      "Adjustable strap"
    ],
    "specifications": {
      "material": "Full-grain leather",
      "dimensions": "16 x 12 x 4 inches",
      "weight": "2.5 lbs",
      "compatibility": "Laptops up to 15 inches"
    },
    "colors": ["Brown", "Black", "Tan"],
    "sizes": ["One Size"],
    "inStock": true,
    "stockQuantity": 25,
    "tags": ["leather", "laptop", "business", "professional"],
    "brand": "IVolex",
    "sku": "LB-001",
    "createdAt": "2024-01-15T10:00:00Z",
    "updatedAt": "2024-01-20T14:30:00Z"
  },
  {
    "id": "p2",
    "name": "Classic Leather Belt",
    "price": 39.99,
    "originalPrice": 49.99,
    "category": "belts",
    "subcategory": "dress-belts",
    "image": "/images/p2.jpg",
    "images": ["/images/p2.jpg", "/images/p2-alt1.jpg"],
    "rating": 4.5,
    "reviewCount": 89,
    "short": "Timeless black leather belt with solid brass buckle.",
    "description": "A classic dress belt that never goes out of style. Made from supple leather with a polished brass buckle, perfect for formal and business attire.",
    "features": [
      "Genuine leather",
      "Brass buckle",
      "Classic design",
      "Adjustable"
    ],
    "specifications": {
      "material": "Genuine leather",
      "buckle": "Solid brass",
      "width": "1.25 inches",
      "lengths": "32-42 inches"
    },
    "colors": ["Black", "Brown"],
    "sizes": ["32", "34", "36", "38", "40", "42"],
    "inStock": true,
    "stockQuantity": 45,
    "tags": ["leather", "belt", "formal", "classic"],
    "brand": "IVolex",
    "sku": "BT-001",
    "createdAt": "2024-01-10T09:00:00Z",
    "updatedAt": "2024-01-18T11:15:00Z"
  },
  {
    "id": "p3",
    "name": "Minimalist Leather Wallet",
    "price": 59.99,
    "originalPrice": 69.99,
    "category": "wallets",
    "subcategory": "bifold-wallets",
    "image": "/images/p3.jpg",
    "images": ["/images/p3.jpg", "/images/p3-alt1.jpg", "/images/p3-alt2.jpg"],
    "rating": 4.6,
    "reviewCount": 203,
    "short": "Slim bifold wallet crafted from smooth leather.",
    "description": "Designed for the modern minimalist, this slim wallet features RFID blocking technology and carefully selected leather for durability and style.",
    "features": [
      "RFID blocking",
      "Slim design",
      "6 card slots",
      "Bill compartment"
    ],
    "specifications": {
      "material": "Top-grain leather",
      "dimensions": "4.3 x 3.4 x 0.3 inches",
      "capacity": "6 cards + bills",
      "rfid": "Yes"
    },
    "colors": ["Black", "Brown", "Navy"],
    "sizes": ["One Size"],
    "inStock": true,
    "stockQuantity": 67,
    "tags": ["leather", "wallet", "minimalist", "rfid"],
    "brand": "IVolex",
    "sku": "WL-001",
    "createdAt": "2024-01-12T08:30:00Z",
    "updatedAt": "2024-01-22T16:45:00Z"
  },
  {
    "id": "p4",
    "name": "Rugged Leather Boots",
    "price": 189.99,
    "originalPrice": 229.99,
    "category": "footwear",
    "subcategory": "boots",
    "image": "/images/p4.jpg",
    "images": ["/images/p4.jpg", "/images/p4-alt1.jpg", "/images/p4-alt2.jpg"],
    "rating": 4.8,
    "reviewCount": 156,
    "short": "Handcrafted leather boots for everyday wear.",
    "description": "Built to last, these handcrafted boots feature premium leather construction, Goodyear welt sole, and timeless design that improves with age.",
    "features": [
      "Goodyear welt construction",
      "Premium leather",
      "Comfortable insole",
      "Durable sole"
    ],
    "specifications": {
      "material": "Full-grain leather",
      "sole": "Goodyear welt",
      "construction": "Handcrafted",
      "heel": "1 inch"
    },
    "colors": ["Brown", "Black"],
    "sizes": ["7", "8", "9", "10", "11", "12"],
    "inStock": true,
    "stockQuantity": 32,
    "tags": ["leather", "boots", "handcrafted", "durable"],
    "brand": "IVolex",
    "sku": "BT-001",
    "createdAt": "2024-01-08T07:00:00Z",
    "updatedAt": "2024-01-25T13:20:00Z"
  }
]
